hololive/__init__.py
hololive/hololive.py
hololive-0.1.4.dist-info/METADATA
hololive-0.1.4.dist-info/WHEEL
hololive-0.1.4.dist-info/top_level.txt
hololive-0.1.4.dist-info/RECORD
