Metadata-Version: 2.1
Name: hololive
Version: 0.1.4
Summary: Gets hololive streams
Home-page: https://github.com/marnixah/hololive-python-api
Author: Marnixah
Author-email: hololive@marnixah.com
License: UNKNOWN
Project-URL: Bug Tracker, https://github.com/marnixah/hololive-python-api/issues
Platform: UNKNOWN
Classifier: Programming Language :: Python :: 3
Classifier: License :: OSI Approved :: MIT License
Classifier: Operating System :: OS Independent
Requires-Python: >=3.6
Requires-Dist: aiohttp
Requires-Dist: python-dateutil
